gender_predictor_module/__init__.py
gender_predictor_module/gender_predictor.keras
gender_predictor_module/model_utils.py
gender_predictor_module/tokenizer.pkl
gender_predictor_rahul-0.1.4.dist-info/METADATA
gender_predictor_rahul-0.1.4.dist-info/WHEEL
gender_predictor_rahul-0.1.4.dist-info/top_level.txt
gender_predictor_rahul-0.1.4.dist-info/RECORD
