Metadata-Version: 2.1
Name: gender-predictor-rahul
Version: 0.1.4
Summary: Gender prediction from names using a trained ML model
Home-page: UNKNOWN
Author: Rahul Patel
License: UNKNOWN
Platform: UNKNOWN
Classifier: Programming Language :: Python :: 3
Requires-Python: >=3.6
Requires-Dist: keras
Requires-Dist: tensorflow
